circuits/__init__.py
circuits/pyparser.py
circuits/six.py
circuits/version.py
circuits/app/__init__.py
circuits/app/daemon.py
circuits/app/dropprivileges.py
circuits/core/__init__.py
circuits/core/bridge.py
circuits/core/components.py
circuits/core/debugger.py
circuits/core/events.py
circuits/core/handlers.py
circuits/core/helpers.py
circuits/core/loader.py
circuits/core/manager.py
circuits/core/pollers.py
circuits/core/timers.py
circuits/core/utils.py
circuits/core/values.py
circuits/core/workers.py
circuits/io/__init__.py
circuits/io/events.py
circuits/io/file.py
circuits/io/notify.py
circuits/io/process.py
circuits/io/serial.py
circuits/net/__init__.py
circuits/net/events.py
circuits/net/sockets.py
circuits/net/utils.py
circuits/node/__init__.py
circuits/node/client.py
circuits/node/events.py
circuits/node/node.py
circuits/node/protocol.py
circuits/node/server.py
circuits/node/utils.py
circuits/protocols/__init__.py
circuits/protocols/http.py
circuits/protocols/line.py
circuits/protocols/websocket.py
circuits/protocols/irc/__init__.py
circuits/protocols/irc/commands.py
circuits/protocols/irc/events.py
circuits/protocols/irc/message.py
circuits/protocols/irc/numerics.py
circuits/protocols/irc/protocol.py
circuits/protocols/irc/replies.py
circuits/protocols/irc/utils.py
circuits/protocols/stomp/__init__.py
circuits/protocols/stomp/client.py
circuits/protocols/stomp/events.py
circuits/protocols/stomp/transport.py
circuits/tools/__init__.py
circuits/web/__init__.py
circuits/web/_httpauth.py
circuits/web/client.py
circuits/web/constants.py
circuits/web/controllers.py
circuits/web/errors.py
circuits/web/events.py
circuits/web/exceptions.py
circuits/web/headers.py
circuits/web/http.py
circuits/web/loggers.py
circuits/web/main.py
circuits/web/processors.py
circuits/web/servers.py
circuits/web/sessions.py
circuits/web/tools.py
circuits/web/url.py
circuits/web/utils.py
circuits/web/wrappers.py
circuits/web/wsgi.py
circuits/web/dispatchers/__init__.py
circuits-3.2.3.dist-info/LICENSE
circuits-3.2.3.dist-info/METADATA
circuits-3.2.3.dist-info/WHEEL
circuits-3.2.3.dist-info/entry_points.txt
circuits-3.2.3.dist-info/top_level.txt
circuits-3.2.3.dist-info/zip-safe
circuits-3.2.3.dist-info/RECORD
